Workbook
Name Co_Role: 'Project Summary'!$B$13:$C$23
Name Headers: #REF!
Name Headers1: #REF!
Name Log: #REF!

Sheet Project Summary
A1: PROJECT COST REPORT
A2: PROJECT NAME
A4: *Note: All figures exclude GST | L4: v01
F5: VARIATIONS
A6: Cost Code | B6: Company | C6: Description/Role | D6: Budget | E6: Approved Contract | F6: Forecast | G6: Approved | H6: Forecast Final Cost | I6: BUDGET VARIANCE | J6: Claimed to Date | K6: Claimed this Month | L6: Remaining to be invoiced
A7: FEES AND CHARGES | J7: =SUMIF(Invoices!$F$7:$F$15,'Project Summary'!C7,Invoices!$G$7:$G$14) -> 0 | K7: =SUMIFS(Invoices!$G$7:$G$8, Invoices!$F$7:$F$8, C7, Invoices!$H$7:$H$8, Invoices!#REF!) -> 0
D8: 0 | E8: =Table4[[#This Row],[Budget]] -> 0 | F8: =SUMIFS(Variations!$E$7:$E$17,Variations!$C$7:$C$17,C8,Variations!$D$7:$D$17,$F$6) -> 0 | G8: =SUMIFS(Variations!$E$7:$E$17,Variations!$C$7:$C$17,C8,Variations!$D$7:$D$17,$G$6) -> 0 | H8: =SUM(E8:G8) -> 0 | I8: =H8-D8 -> 0 | J8: =SUMIF(Invoices!$F$7:$F$15,'Project Summary'!C8,Invoices!$G$7:$G$14) -> 0 | K8: =SUMIFS(Invoices!$G$7:$G$8, Invoices!$F$7:$F$8, C8, Invoices!$H$7:$H$8, Invoices!#REF!) -> 0 | L8: =H8-J8 -> 0
D9: 0 | E9: =Table4[[#This Row],[Budget]] -> 0 | F9: =SUMIFS(Variations!$E$7:$E$17,Variations!$C$7:$C$17,C9,Variations!$D$7:$D$17,$F$6) -> 0 | G9: =SUMIFS(Variations!$E$7:$E$17,Variations!$C$7:$C$17,C9,Variations!$D$7:$D$17,$G$6) -> 0 | H9: =SUM(E9:G9) -> 0 | I9: =H9-D9 -> 0 | J9: =SUMIF(Invoices!$F$7:$F$15,'Project Summary'!C9,Invoices!$G$7:$G$14) -> 0 | K9: =SUMIFS(Invoices!$G$7:$G$8, Invoices!$F$7:$F$8, C9, Invoices!$H$7:$H$8, Invoices!#REF!) -> 0 | L9: =H9-J9 -> 0
D10: 0 | E10: =Table4[[#This Row],[Budget]] -> 0 | F10: =SUMIFS(Variations!$E$7:$E$17,Variations!$C$7:$C$17,C10,Variations!$D$7:$D$17,$F$6) -> 0 | G10: =SUMIFS(Variations!$E$7:$E$17,Variations!$C$7:$C$17,C10,Variations!$D$7:$D$17,$G$6) -> 0 | H10: =SUM(E10:G10) -> 0 | I10: =H10-D10 -> 0 | J10: =SUMIF(Invoices!$F$7:$F$15,'Project Summary'!C10,Invoices!$G$7:$G$14) -> 0 | K10: =SUMIFS(Invoices!$G$7:$G$8, Invoices!$F$7:$F$8, C10, Invoices!$H$7:$H$8, Invoices!#REF!) -> 0 | L10: =H10-J10 -> 0
A11: Sub-Total | D11: =SUBTOTAL(109,Table4[Budget]) -> 0 | E11: =SUBTOTAL(109,Table4[Approved Contract]) -> 0 | F11: =SUBTOTAL(109,Table4[Forecast]) -> 0 | G11: =SUBTOTAL(109,Table4[Approved]) -> 0 | H11: =SUBTOTAL(109,Table4[Forecast Final Cost]) -> 0 | I11: =SUBTOTAL(109,Table4[BUDGET VARIANCE]) -> 0 | J11: =SUBTOTAL(109,Table4[Claimed to Date]) -> 0 | L11: =SUBTOTAL(109,Table4[Remaining to be invoiced]) -> 0
A13: Cost Code | B13: Company | C13: Description/Role | D13: Budget | E13: Approved Contract | F13: Forecast | G13: Approved | H13: Forecast Final Cost | I13: BUDGET VARIANCE | J13: Claimed to Date | K13: Claimed this Month | L13: Remaining to be invoiced
A14: CONSULTANTS | F14: =SUMIF(Invoices!$F$7:$F$15,'Project Summary'!#REF!,Invoices!$G$7:$G$14) -> 0 | G14: =SUMIFS(Variations!$E$7:$E$17,Variations!$C$7:$C$17,C14,Variations!$D$7:$D$17,$G$6) -> 0 | H14: =SUM(E14:G14) -> 0 | I14: =H14-D14 -> 0 | J14: =SUMIF(Invoices!$F$7:$F$15,'Project Summary'!C14,Invoices!$G$7:$G$14) -> 0 | K14: =SUMIFS(Invoices!$G$7:$G$8, Invoices!$F$7:$F$8, C14, Invoices!$H$7:$H$8, Invoices!#REF!) -> 0 | L14: =H14-J14 -> 0
D15: 0 | E15: 0 | F15: =SUMIFS(Variations!$E$7:$E$17,Variations!$C$7:$C$17,C15,Variations!$D$7:$D$17,$F$6) -> 0 | G15: =SUMIFS(Variations!$E$7:$E$17,Variations!$C$7:$C$17,C15,Variations!$D$7:$D$17,$G$6) -> 0 | H15: =SUM(E15:G15) -> 0 | I15: =H15-D15 -> 0 | J15: =SUMIF(Invoices!$F$7:$F$15,'Project Summary'!C15,Invoices!$G$7:$G$14) -> 0 | K15: =SUMIFS(Invoices!$G$7:$G$8, Invoices!$F$7:$F$8, C15, Invoices!$H$7:$H$8, Invoices!#REF!) -> 0 | L15: =H15-J15 -> 0
D16: 0 | E16: 0 | F16: =SUMIFS(Variations!$E$7:$E$17,Variations!$C$7:$C$17,C16,Variations!$D$7:$D$17,$F$6) -> 0 | G16: =SUMIFS(Variations!$E$7:$E$17,Variations!$C$7:$C$17,C16,Variations!$D$7:$D$17,$G$6) -> 0 | H16: =SUM(E16:G16) -> 0 | I16: =H16-D16 -> 0 | J16: =SUMIF(Invoices!$F$7:$F$15,'Project Summary'!C16,Invoices!$G$7:$G$14) -> 0 | K16: =SUMIFS(Invoices!$G$7:$G$8, Invoices!$F$7:$F$8, C16, Invoices!$H$7:$H$8, Invoices!#REF!) -> 0 | L16: =H16-J16 -> 0
D17: 0 | E17: 0 | F17: =SUMIFS(Variations!$E$7:$E$17,Variations!$C$7:$C$17,C17,Variations!$D$7:$D$17,$F$6) -> 0 | G17: =SUMIFS(Variations!$E$7:$E$17,Variations!$C$7:$C$17,C17,Variations!$D$7:$D$17,$G$6) -> 0 | H17: =SUM(E17:G17) -> 0 | I17: =H17-D17 -> 0 | J17: =SUMIF(Invoices!$F$7:$F$15,'Project Summary'!C17,Invoices!$G$7:$G$14) -> 0 | K17: =SUMIFS(Invoices!$G$7:$G$8, Invoices!$F$7:$F$8, C17, Invoices!$H$7:$H$8, Invoices!#REF!) -> 0 | L17: =H17-J17 -> 0
D18: 0 | E18: 0 | F18: =SUMIFS(Variations!$E$7:$E$17,Variations!$C$7:$C$17,C18,Variations!$D$7:$D$17,$F$6) -> 0 | G18: =SUMIFS(Variations!$E$7:$E$17,Variations!$C$7:$C$17,C18,Variations!$D$7:$D$17,$G$6) -> 0 | H18: =SUM(E18:G18) -> 0 | I18: =H18-D18 -> 0 | J18: =SUMIF(Invoices!$F$7:$F$15,'Project Summary'!C18,Invoices!$G$7:$G$14) -> 0 | K18: =SUMIFS(Invoices!$G$7:$G$8, Invoices!$F$7:$F$8, C18, Invoices!$H$7:$H$8, Invoices!#REF!) -> 0 | L18: =H18-J18 -> 0
D19: 0 | E19: 0 | F19: =SUMIFS(Variations!$E$7:$E$17,Variations!$C$7:$C$17,C19,Variations!$D$7:$D$17,$F$6) -> 0 | G19: =SUMIFS(Variations!$E$7:$E$17,Variations!$C$7:$C$17,C19,Variations!$D$7:$D$17,$G$6) -> 0 | H19: =SUM(E19:G19) -> 0 | I19: =H19-D19 -> 0 | J19: =SUMIF(Invoices!$F$7:$F$15,'Project Summary'!C19,Invoices!$G$7:$G$14) -> 0 | K19: =SUMIFS(Invoices!$G$7:$G$8, Invoices!$F$7:$F$8, C19, Invoices!$H$7:$H$8, Invoices!#REF!) -> 0 | L19: =H19-J19 -> 0
A20: Sub-Total | D20: =SUBTOTAL(109,Table6[Budget]) -> 0 | E20: =SUBTOTAL(109,Table6[Approved Contract]) -> 0 | F20: =SUBTOTAL(109,Table6[Forecast]) -> 0 | G20: =SUBTOTAL(109,Table6[Approved]) -> 0 | H20: =SUBTOTAL(109,Table6[Forecast Final Cost]) -> 0 | I20: =SUBTOTAL(109,Table6[BUDGET VARIANCE]) -> 0 | J20: =SUBTOTAL(109,Table6[Claimed to Date]) -> 0 | K20: =SUM(K15:K19) -> 0 | L20: =SUBTOTAL(109,Table6[Remaining to be invoiced]) -> 0
A22: Cost Code | B22: Company | C22: Description/Role | D22: Budget | E22: Approved Contract | F22: Forecast | G22: Approved | H22: Forecast Final Cost | I22: BUDGET VARIANCE | J22: Claimed to Date | K22: Claimed this Month | L22: Remaining to be invoiced
A23: CONSTRUCTION | K23: =SUMIFS(Invoices!$G$7:$G$8, Invoices!$F$7:$F$8,#REF!, Invoices!$H$7:$H$8, Invoices!#REF!) -> 0
D24: 0 | E24: 0 | F24: =SUMIFS(Variations!$E$7:$E$17,Variations!$C$7:$C$17,C24,Variations!$D$7:$D$17,$F$6) -> 0 | G24: =SUMIFS(Variations!$E$7:$E$17,Variations!$C$7:$C$17,C24,Variations!$D$7:$D$17,$G$6) -> 0 | H24: =SUM(E24:G24) -> 0 | I24: =H24-D24 -> 0 | J24: =SUMIF(Invoices!$F$7:$F$15,'Project Summary'!C24,Invoices!$G$7:$G$14) -> 0 | K24: =SUMIFS(Invoices!$G$7:$G$8, Invoices!$F$7:$F$8, C24, Invoices!$H$7:$H$8, Invoices!#REF!) -> 0 | L24: =H24-J24 -> 0
D25: 0 | E25: 0 | F25: =SUMIFS(Variations!$E$7:$E$17,Variations!$C$7:$C$17,C25,Variations!$D$7:$D$17,$F$6) -> 0 | G25: =SUMIFS(Variations!$E$7:$E$17,Variations!$C$7:$C$17,C25,Variations!$D$7:$D$17,$G$6) -> 0 | H25: =SUM(E25:G25) -> 0 | I25: =H25-D25 -> 0 | J25: =SUMIF(Invoices!$F$7:$F$15,'Project Summary'!C25,Invoices!$G$7:$G$14) -> 0 | K25: =SUMIFS(Invoices!$G$7:$G$8, Invoices!$F$7:$F$8, C25, Invoices!$H$7:$H$8, Invoices!#REF!) -> 0 | L25: =H25-J25 -> 0
D26: 0 | E26: 0 | F26: =SUMIFS(Variations!$E$7:$E$17,Variations!$C$7:$C$17,C26,Variations!$D$7:$D$17,$F$6) -> 0 | G26: =SUMIFS(Variations!$E$7:$E$17,Variations!$C$7:$C$17,C26,Variations!$D$7:$D$17,$G$6) -> 0 | H26: =SUM(E26:G26) -> 0 | I26: =H26-D26 -> 0 | J26: =SUMIF(Invoices!$F$7:$F$15,'Project Summary'!C26,Invoices!$G$7:$G$14) -> 0 | K26: =SUMIFS(Invoices!$G$7:$G$8, Invoices!$F$7:$F$8, C26, Invoices!$H$7:$H$8, Invoices!#REF!) -> 0 | L26: =H26-J26 -> 0
D27: 0 | E27: 0 | F27: =SUMIFS(Variations!$E$7:$E$17,Variations!$C$7:$C$17,C27,Variations!$D$7:$D$17,$F$6) -> 0 | G27: =SUMIFS(Variations!$E$7:$E$17,Variations!$C$7:$C$17,C27,Variations!$D$7:$D$17,$G$6) -> 0 | H27: =SUM(E27:G27) -> 0 | I27: =H27-D27 -> 0 | J27: =SUMIF(Invoices!$F$7:$F$15,'Project Summary'!C27,Invoices!$G$7:$G$14) -> 0 | K27: =SUMIFS(Invoices!$G$7:$G$8, Invoices!$F$7:$F$8, C27, Invoices!$H$7:$H$8, Invoices!#REF!) -> 0 | L27: =H27-J27 -> 0
A28: Sub-Total | D28: =SUBTOTAL(109,PC_Table[Budget]) -> 0 | E28: =SUBTOTAL(109,PC_Table[Approved Contract]) -> 0 | F28: =SUBTOTAL(109,PC_Table[Forecast]) -> 0 | G28: =SUBTOTAL(109,PC_Table[Approved]) -> 0 | H28: =SUBTOTAL(109,PC_Table[Forecast Final Cost]) -> 0 | I28: =SUBTOTAL(109,PC_Table[BUDGET VARIANCE]) -> 0 | J28: =SUBTOTAL(109,PC_Table[Claimed to Date]) -> 0 | K28: =SUM(K24:K27) -> 0 | L28: =SUBTOTAL(109,PC_Table[Remaining to be invoiced]) -> 0
A29: Cost Code | B29: Company | C29: Description/Role | D29: Budget | E29: Approved Contract | F29: Forecast | G29: Approved | H29: Forecast Final Cost | I29: BUDGET VARIANCE | J29: Claimed to Date | K29: Claimed this Month | L29: Remaining to be invoiced
A30: CONTINGENCY | D30: =0.1*SUM(D24:D26) -> 0 | E30: =Table8[[#This Row],[Budget]] -> 0 | F30: =SUMIFS(Variations!$E$7:$E$17,Variations!$C$7:$C$17,C30,Variations!$D$7:$D$17,$F$6) -> 0 | G30: =SUMIFS(Variations!$E$7:$E$17,Variations!$C$7:$C$17,C30,Variations!$D$7:$D$17,$G$6) -> 0 | K30: =SUMIFS(Invoices!$G$7:$G$8, Invoices!$F$7:$F$8, C30, Invoices!$H$7:$H$8, Invoices!#REF!) -> 0
D31: =0.1*SUM(D25:D27) -> 0 | E31: =Table8[[#This Row],[Budget]] -> 0 | F31: =SUMIFS(Variations!$E$7:$E$17,Variations!$C$7:$C$17,C31,Variations!$D$7:$D$17,$F$6) -> 0 | G31: =SUMIFS(Variations!$E$7:$E$17,Variations!$C$7:$C$17,C31,Variations!$D$7:$D$17,$G$6) -> 0 | H31: =SUM(E31:G31) -> 0 | I31: =H31-D31 -> 0 | J31: =SUMIF(Invoices!$F$7:$F$15,C31,Invoices!$G$7:$G$8) -> 0 | K31: =SUMIFS(Invoices!$G$7:$G$8, Invoices!$F$7:$F$8, C31, Invoices!$H$7:$H$8, Invoices!#REF!) -> 0 | L31: =E31+G31-J31 -> 0
A32: Sub-Total | D32: =SUM(D31) -> 0 | E32: =E31 -> 0 | F32: =SUBTOTAL(109,Table8[Forecast]) -> 0 | G32: =SUBTOTAL(109,Table8[Approved]) -> 0 | H32: =SUBTOTAL(109,Table8[Forecast Final Cost]) -> 0 | J32: =SUBTOTAL(109,Table8[Claimed to Date]) -> 0 | L32: =SUBTOTAL(109,Table8[Remaining to be invoiced]) -> 0
A34: GRAND TOTAL | B34: Excluding PM fee | D34: =SUM(D11,D32,D28,D20) -> 0 | E34: =SUM(E11,E32,E28,E20) -> 0 | F34: =SUM(F11,F32,F28,F20) -> 0 | G34: =SUM(G11,G32,G28,G20) -> 0 | H34: =SUM(H11,H32,H28,H20) -> 0 | I34: =SUM(I11,I32,I28,I20) -> 0 | J34: =SUM(J11,J32,J28,J20) -> 0 | K34: =SUM(K11,K32,K28,K20) -> 0 | L34: =SUM(L11,L32,L28,L20) -> 0

Sheet Invoices
B1: PROJECT COST REPORT - INVOICES
B2: PROJEC NAME
B4: *Note: All figures exclude GST | I4: ='Project Summary'!L4 -> v01
B6: Date | C6: Company | D6: PO Number | E6: Invoice Number | F6: Description/Role | G6: Amount | H6: Current Month | I6: Paid? | J6: Column1
B15: TOTALS | G15: =SUM(G7:G14) -> 0

Sheet Variations
A1: PROJECT COST REPORT - VARIATIONS
A2: PROJEC NAME
A4: *Note: All figures exclude GST | F4: ='Project Summary'!L4 -> v01
A6: Date Submitted | B6: Description | C6: Variation To | D6: Status | E6: Amount Approved | F6: Date Approved
H7: Forecast
H8: Approved
H9: Estimate Cost
H10: Rejected
H11: Withdrawn
A18: Total | E18: =SUBTOTAL(109,Table1[Amount Approved]) -> 0
