Workbook

Sheet Summary
A1: Project Cost Plan - Residential House Template
A2: Reusable residential house cost framework
A3: 02-skills/systems/Cost_Plan_vNN.xlsx
A4: All figures exclude GST | Framework adapted from L09-House-Price.xlsx
K5: 46172
A6: Cost Code | B6: Category | C6: Cost Items | D6: Budget | E6: Approved Contract | F6: Forecast | G6: Approved Variations | H6: Forecast Final Cost | I6: Budget Variance | J6: Claimed to Date | K6: This Month | L6: Remaining
A7: 1.1 | B7: Fees and charges | C7: AUTHORITIES FEES | D7: 3788.13 | E7: 0 | F7: =SUMIF(Variations!$B$5:$B$500,C7,Variations!$G$5:$G$500) | G7: =SUMIF(Variations!$B$5:$B$500,C7,Variations!$G$5:$G$500) | H7: =SUM(E7:G7) | I7: =D7-H7 | J7: =SUMIF(Invoices!$E$5:$E$500,C7,Invoices!$F$5:$F$500) | K7: =SUMIFS(Invoices!$F$5:$F$500,Invoices!$A$5:$A$500,">="&K$5,Invoices!$A$5:$A$500,"<"&EDATE(K$5,1),Invoices!$E$5:$E$500,C7) | L7: =D7-J7
A8: 1.3 | B8: Fees and charges | C8: HOW & LSL | D8: 10011.48 | E8: 0 | F8: =SUMIF(Variations!$B$5:$B$500,C8,Variations!$G$5:$G$500) | G8: =SUMIF(Variations!$B$5:$B$500,C8,Variations!$G$5:$G$500) | H8: =SUM(E8:G8) | I8: =D8-H8 | J8: =SUMIF(Invoices!$E$5:$E$500,C8,Invoices!$F$5:$F$500) | K8: =SUMIFS(Invoices!$F$5:$F$500,Invoices!$A$5:$A$500,">="&K$5,Invoices!$A$5:$A$500,"<"&EDATE(K$5,1),Invoices!$E$5:$E$500,C8) | L8: =D8-J8
C9: SUBTOTAL - Fees and charges | D9: =SUM(D7:D8) | E9: =SUM(E7:E8) | F9: =SUM(F7:F8) | G9: =SUM(G7:G8) | H9: =SUM(H7:H8) | I9: =SUM(I7:I8) | J9: =SUM(J7:J8) | K9: =SUM(K7:K8) | L9: =SUM(L7:L8)
A11: 1.2 | B11: Consultants | C11: CONSULTANTS | D11: 1352.9 | E11: 0 | F11: =SUMIF(Variations!$B$5:$B$500,C11,Variations!$G$5:$G$500) | G11: =SUMIF(Variations!$B$5:$B$500,C11,Variations!$G$5:$G$500) | H11: =SUM(E11:G11) | I11: =D11-H11 | J11: =SUMIF(Invoices!$E$5:$E$500,C11,Invoices!$F$5:$F$500) | K11: =SUMIFS(Invoices!$F$5:$F$500,Invoices!$A$5:$A$500,">="&K$5,Invoices!$A$5:$A$500,"<"&EDATE(K$5,1),Invoices!$E$5:$E$500,C11) | L11: =D11-J11
A12: 2.1 | B12: Consultants | C12: SURVEYORS | D12: 4230.34 | E12: 0 | F12: =SUMIF(Variations!$B$5:$B$500,C12,Variations!$G$5:$G$500) | G12: =SUMIF(Variations!$B$5:$B$500,C12,Variations!$G$5:$G$500) | H12: =SUM(E12:G12) | I12: =D12-H12 | J12: =SUMIF(Invoices!$E$5:$E$500,C12,Invoices!$F$5:$F$500) | K12: =SUMIFS(Invoices!$F$5:$F$500,Invoices!$A$5:$A$500,">="&K$5,Invoices!$A$5:$A$500,"<"&EDATE(K$5,1),Invoices!$E$5:$E$500,C12) | L12: =D12-J12
C13: SUBTOTAL - Consultants | D13: =SUM(D11:D12) | E13: =SUM(E11:E12) | F13: =SUM(F11:F12) | G13: =SUM(G11:G12) | H13: =SUM(H11:H12) | I13: =SUM(I11:I12) | J13: =SUM(J11:J12) | K13: =SUM(K11:K12) | L13: =SUM(L11:L12)
A15: 1.4 | B15: Construction | C15: TEMP SERVICES (SITE AMMENITIES) | D15: 3246.97 | E15: 0 | F15: =SUMIF(Variations!$B$5:$B$500,C15,Variations!$G$5:$G$500) | G15: =SUMIF(Variations!$B$5:$B$500,C15,Variations!$G$5:$G$500) | H15: =SUM(E15:G15) | I15: =D15-H15 | J15: =SUMIF(Invoices!$E$5:$E$500,C15,Invoices!$F$5:$F$500) | K15: =SUMIFS(Invoices!$F$5:$F$500,Invoices!$A$5:$A$500,">="&K$5,Invoices!$A$5:$A$500,"<"&EDATE(K$5,1),Invoices!$E$5:$E$500,C15) | L15: =D15-J15
A16: 1.5 | B16: Construction | C16: SUPERVISION | D16: 16234.84 | E16: 0 | F16: =SUMIF(Variations!$B$5:$B$500,C16,Variations!$G$5:$G$500) | G16: =SUMIF(Variations!$B$5:$B$500,C16,Variations!$G$5:$G$500) | H16: =SUM(E16:G16) | I16: =D16-H16 | J16: =SUMIF(Invoices!$E$5:$E$500,C16,Invoices!$F$5:$F$500) | K16: =SUMIFS(Invoices!$F$5:$F$500,Invoices!$A$5:$A$500,">="&K$5,Invoices!$A$5:$A$500,"<"&EDATE(K$5,1),Invoices!$E$5:$E$500,C16) | L16: =D16-J16
A17: 2.2 | B17: Construction | C17: EARTHWORKS | D17: 10293.76 | E17: 0 | F17: =SUMIF(Variations!$B$5:$B$500,C17,Variations!$G$5:$G$500) | G17: =SUMIF(Variations!$B$5:$B$500,C17,Variations!$G$5:$G$500) | H17: =SUM(E17:G17) | I17: =D17-H17 | J17: =SUMIF(Invoices!$E$5:$E$500,C17,Invoices!$F$5:$F$500) | K17: =SUMIFS(Invoices!$F$5:$F$500,Invoices!$A$5:$A$500,">="&K$5,Invoices!$A$5:$A$500,"<"&EDATE(K$5,1),Invoices!$E$5:$E$500,C17) | L17: =D17-J17
A18: 2.3 | B18: Construction | C18: TERMITE TREATMENT | D18: 979.69 | E18: 0 | F18: =SUMIF(Variations!$B$5:$B$500,C18,Variations!$G$5:$G$500) | G18: =SUMIF(Variations!$B$5:$B$500,C18,Variations!$G$5:$G$500) | H18: =SUM(E18:G18) | I18: =D18-H18 | J18: =SUMIF(Invoices!$E$5:$E$500,C18,Invoices!$F$5:$F$500) | K18: =SUMIFS(Invoices!$F$5:$F$500,Invoices!$A$5:$A$500,">="&K$5,Invoices!$A$5:$A$500,"<"&EDATE(K$5,1),Invoices!$E$5:$E$500,C18) | L18: =D18-J18
A19: 3.1 | B19: Construction | C19: FOUNDATION PIERS | D19: 18083.2 | E19: 0 | F19: =SUMIF(Variations!$B$5:$B$500,C19,Variations!$G$5:$G$500) | G19: =SUMIF(Variations!$B$5:$B$500,C19,Variations!$G$5:$G$500) | H19: =SUM(E19:G19) | I19: =D19-H19 | J19: =SUMIF(Invoices!$E$5:$E$500,C19,Invoices!$F$5:$F$500) | K19: =SUMIFS(Invoices!$F$5:$F$500,Invoices!$A$5:$A$500,">="&K$5,Invoices!$A$5:$A$500,"<"&EDATE(K$5,1),Invoices!$E$5:$E$500,C19) | L19: =D19-J19
A20: 3.2 | B20: Construction | C20: CONCRETE WORKS | D20: 35427.81 | E20: 0 | F20: =SUMIF(Variations!$B$5:$B$500,C20,Variations!$G$5:$G$500) | G20: =SUMIF(Variations!$B$5:$B$500,C20,Variations!$G$5:$G$500) | H20: =SUM(E20:G20) | I20: =D20-H20 | J20: =SUMIF(Invoices!$E$5:$E$500,C20,Invoices!$F$5:$F$500) | K20: =SUMIFS(Invoices!$F$5:$F$500,Invoices!$A$5:$A$500,">="&K$5,Invoices!$A$5:$A$500,"<"&EDATE(K$5,1),Invoices!$E$5:$E$500,C20) | L20: =D20-J20
A21: 4.1 | B21: Construction | C21: WALL FRAMING & ROOF TRUSSES | D21: 58566.18 | E21: 0 | F21: =SUMIF(Variations!$B$5:$B$500,C21,Variations!$G$5:$G$500) | G21: =SUMIF(Variations!$B$5:$B$500,C21,Variations!$G$5:$G$500) | H21: =SUM(E21:G21) | I21: =D21-H21 | J21: =SUMIF(Invoices!$E$5:$E$500,C21,Invoices!$F$5:$F$500) | K21: =SUMIFS(Invoices!$F$5:$F$500,Invoices!$A$5:$A$500,">="&K$5,Invoices!$A$5:$A$500,"<"&EDATE(K$5,1),Invoices!$E$5:$E$500,C21) | L21: =D21-J21
A22: 4.2 | B22: Construction | C22: STRUCTURAL STEEL | D22: 7754.19 | E22: 0 | F22: =SUMIF(Variations!$B$5:$B$500,C22,Variations!$G$5:$G$500) | G22: =SUMIF(Variations!$B$5:$B$500,C22,Variations!$G$5:$G$500) | H22: =SUM(E22:G22) | I22: =D22-H22 | J22: =SUMIF(Invoices!$E$5:$E$500,C22,Invoices!$F$5:$F$500) | K22: =SUMIFS(Invoices!$F$5:$F$500,Invoices!$A$5:$A$500,">="&K$5,Invoices!$A$5:$A$500,"<"&EDATE(K$5,1),Invoices!$E$5:$E$500,C22) | L22: =D22-J22
A23: 4.3 | B23: Construction | C23: MOBILE CRANE HIRE | D23: 4041.96 | E23: 0 | F23: =SUMIF(Variations!$B$5:$B$500,C23,Variations!$G$5:$G$500) | G23: =SUMIF(Variations!$B$5:$B$500,C23,Variations!$G$5:$G$500) | H23: =SUM(E23:G23) | I23: =D23-H23 | J23: =SUMIF(Invoices!$E$5:$E$500,C23,Invoices!$F$5:$F$500) | K23: =SUMIFS(Invoices!$F$5:$F$500,Invoices!$A$5:$A$500,">="&K$5,Invoices!$A$5:$A$500,"<"&EDATE(K$5,1),Invoices!$E$5:$E$500,C23) | L23: =D23-J23
A24: 4.4 | B24: Construction | C24: WINDOW SUPPLY | D24: 19710.84 | E24: 0 | F24: =SUMIF(Variations!$B$5:$B$500,C24,Variations!$G$5:$G$500) | G24: =SUMIF(Variations!$B$5:$B$500,C24,Variations!$G$5:$G$500) | H24: =SUM(E24:G24) | I24: =D24-H24 | J24: =SUMIF(Invoices!$E$5:$E$500,C24,Invoices!$F$5:$F$500) | K24: =SUMIFS(Invoices!$F$5:$F$500,Invoices!$A$5:$A$500,">="&K$5,Invoices!$A$5:$A$500,"<"&EDATE(K$5,1),Invoices!$E$5:$E$500,C24) | L24: =D24-J24
A25: 4.5 | B25: Construction | C25: MASONRY | D25: 31879.77 | E25: 0 | F25: =SUMIF(Variations!$B$5:$B$500,C25,Variations!$G$5:$G$500) | G25: =SUMIF(Variations!$B$5:$B$500,C25,Variations!$G$5:$G$500) | H25: =SUM(E25:G25) | I25: =D25-H25 | J25: =SUMIF(Invoices!$E$5:$E$500,C25,Invoices!$F$5:$F$500) | K25: =SUMIFS(Invoices!$F$5:$F$500,Invoices!$A$5:$A$500,">="&K$5,Invoices!$A$5:$A$500,"<"&EDATE(K$5,1),Invoices!$E$5:$E$500,C25) | L25: =D25-J25
A26: 4.6 | B26: Construction | C26: SCAFFOLDING | D26: 16899.88 | E26: 0 | F26: =SUMIF(Variations!$B$5:$B$500,C26,Variations!$G$5:$G$500) | G26: =SUMIF(Variations!$B$5:$B$500,C26,Variations!$G$5:$G$500) | H26: =SUM(E26:G26) | I26: =D26-H26 | J26: =SUMIF(Invoices!$E$5:$E$500,C26,Invoices!$F$5:$F$500) | K26: =SUMIFS(Invoices!$F$5:$F$500,Invoices!$A$5:$A$500,">="&K$5,Invoices!$A$5:$A$500,"<"&EDATE(K$5,1),Invoices!$E$5:$E$500,C26) | L26: =D26-J26
... A52: 6.5 | B52: Construction | C52: CLEANING | D52: 9496 | E52: 0 | F52: =SUMIF(Variations!$B$5:$B$500,C52,Variations!$G$5:$G$500) | G52: =SUMIF(Variations!$B$5:$B$500,C52,Variations!$G$5:$G$500) | H52: =SUM(E52:G52) | I52: =D52-H52 | J52: =SUMIF(Invoices!$E$5:$E$500,C52,Invoices!$F$5:$F$500) | K52: =SUMIFS(Invoices!$F$5:$F$500,Invoices!$A$5:$A$500,">="&K$5,Invoices!$A$5:$A$500,"<"&EDATE(K$5,1),Invoices!$E$5:$E$500,C52) | L52: =D52-J52
C53: SUBTOTAL - Construction | D53: =SUM(D15:D52) | E53: =SUM(E15:E52) | F53: =SUM(F15:F52) | G53: =SUM(G15:G52) | H53: =SUM(H15:H52) | I53: =SUM(I15:I52) | J53: =SUM(J15:J52) | K53: =SUM(K15:K52) | L53: =SUM(L15:L52)
A55: 4.99 | B55: Contingency / allowances | C55: Construction contingency | D55: =D53*7.5% | E55: 0 | F55: =SUMIF(Variations!$B$5:$B$500,C55,Variations!$G$5:$G$500) | G55: =SUMIF(Variations!$B$5:$B$500,C55,Variations!$G$5:$G$500) | H55: =SUM(E55:G55) | I55: =D55-H55 | J55: =SUMIF(Invoices!$E$5:$E$500,C55,Invoices!$F$5:$F$500) | K55: =SUMIFS(Invoices!$F$5:$F$500,Invoices!$A$5:$A$500,">="&K$5,Invoices!$A$5:$A$500,"<"&EDATE(K$5,1),Invoices!$E$5:$E$500,C55) | L55: =D55-J55
C56: SUBTOTAL - Contingency / allowances | D56: =SUM(D55:D55) | E56: =SUM(E55:E55) | F56: =SUM(F55:F55) | G56: =SUM(G55:G55) | H56: =SUM(H55:H55) | I56: =SUM(I55:I55) | J56: =SUM(J55:J55) | K56: =SUM(K55:K55) | L56: =SUM(L55:L55)
C58: GRAND TOTAL - HOUSE COST FRAMEWORK | D58: =D9+D13+D53+D56 | E58: =E9+E13+E53+E56 | F58: =F9+F13+F53+F56 | G58: =G9+G13+G53+G56 | H58: =H9+H13+H53+H56 | I58: =I9+I13+I53+I56 | J58: =J9+J13+J53+J56 | K58: =K9+K13+K53+K56 | L58: =L9+L13+L53+L56

Sheet Invoices
A1: INVOICES REGISTER
A2: Reusable residential house cost framework
A4: Date | B4: Company | C4: PO Number | D4: Invoice Number | E4: Cost Item | F4: Amount | G4: Current Month | H4: Paid?

Sheet Variations
A1: VARIATIONS REGISTER
A2: Reusable residential house cost framework
A4: Date Submitted | B4: Cost Item | C4: Variation To | D4: Status | E4: Amount | F4: Date Approved | G4: Approved Amount
